{
  "type": "selector",
  "label": "root",
  "children": [
    {
      "type": "check",
      "name": "HasOwnerCommand",
      "params": {},
      "child": {
        "type": "action",
        "name": "HandleOwnerCommand",
        "params": {}
      }
    },
    {
      "type": "selector",
      "children": [
        {
          "type": "action",
          "name": "UseOffensiveBuff",
          "params": {}
        },
        {
          "type": "action",
          "name": "UseDefensiveBuff",
          "params": {}
        },
        {
          "type": "action",
          "name": "UseOwnerBuff",
          "params": {}
        }
      ],
      "label": "Buffs"
    },
    {
      "type": "check",
      "name": "OwnerUnderAttack",
      "params": {
        "count": 4
      },
      "child": {
        "type": "action",
        "name": "UseCastling",
        "params": {}
      }
    },
    {
      "type": "selector",
      "children": [
        {
          "type": "check",
          "name": "HasValidTarget",
          "params": {},
          "child": {
            "type": "selector",
            "children": [
              {
                "type": "action",
                "name": "UseMainSkill",
                "params": {}
              },
              {
                "type": "action",
                "name": "UseAoESkill",
                "params": {}
              },
              {
                "type": "check",
                "name": "InAttackRange",
                "params": {},
                "child": {
                  "type": "action",
                  "name": "AttackTarget",
                  "params": {}
                }
              },
              {
                "type": "action",
                "name": "ChaseTarget",
                "params": {}
              }
            ],
            "label": "Ataques"
          }
        },
        {
          "type": "check",
          "name": "CanEngage",
          "params": {},
          "child": {
            "type": "action",
            "name": "AcquireTarget",
            "params": {}
          }
        }
      ],
      "label": "Engajar"
    },
    {
      "type": "selector",
      "children": [
        {
          "type": "check",
          "name": "TooFarFromOwner",
          "params": {
            "dist": 4
          },
          "child": {
            "type": "action",
            "name": "MoveToOwner",
            "params": {}
          }
        },
        {
          "type": "action",
          "name": "Idle",
          "params": {}
        }
      ],
      "label": "Ocioso"
    }
  ]
}
